Module/Math_module.py
Module/__init__.py
mathmodule14147-0.1.0.dist-info/METADATA
mathmodule14147-0.1.0.dist-info/WHEEL
mathmodule14147-0.1.0.dist-info/top_level.txt
mathmodule14147-0.1.0.dist-info/RECORD
