Metadata-Version: 2.4
Name: Mathmodule14147
Version: 0.1.0
Summary: Maths Functions
Author: Ghanisth Mittal
Author-email: ghanisthmittal1@gmail.com
Classifier: Programming Language :: Python :: 3
Classifier: License :: OSI Approved :: MIT License
Classifier: Operating System :: OS Independent
Requires-Python: >=3.6
Dynamic: author
Dynamic: author-email
Dynamic: classifier
Dynamic: description
Dynamic: description-content-type
Dynamic: requires-python
Dynamic: summary
